interaction_simple.py
interaction_simple-1.0.1.dist-info/LICENSE
interaction_simple-1.0.1.dist-info/METADATA
interaction_simple-1.0.1.dist-info/WHEEL
interaction_simple-1.0.1.dist-info/top_level.txt
interaction_simple-1.0.1.dist-info/RECORD
