Metadata-Version: 2.1
Name: interaction_simple
Version: 1.0.1
Summary: "It will have a simple conversation with client.",
Author: Akash Ojha
Keywords: interaction
Requires-Python: >=3.6
License-File: LICENSE
